[
  {
    "title": "Kiezgarten: Urbanes Gartenprojekt in Neukölln",
    "description": "Wir suchen Investoren und Gartenliebhaber, um eine Brachfläche in einen Gemeinschaftsgarten zu verwandeln.",
    "status": "Offen",
    "link": "https://github.com/smartlivingberlin/smartlivingberlin.github.io/issues/new?template=projekt-vorschlagen.yml"
  },
  {
    "title": "Aufstockung Altbau Prenzlauer Berg",
    "description": "Projektidee: Aufstockung eines Altbaus mit Holzmodulen. Wir suchen Architekten und Finanzierungspartner.",
    "status": "In Planung",
    "link": "https://github.com/smartlivingberlin/smartlivingberlin.github.io/issues/new?template=projekt-vorschlagen.yml"
  }
]
